setup.py
src/ohos/__init__.py
src/ohos/constants.py
src/ohos/error.py
src/ohos/exception.py
src/ohos/utils.py
src/ohos/config/__init__.py
src/ohos/config/config_manager.py
src/ohos/drivers/__init__.py
src/ohos/drivers/build_only_driver_lite.py
src/ohos/drivers/c_driver_lite.py
src/ohos/drivers/constants.py
src/ohos/drivers/cpp_driver.py
src/ohos/drivers/cpp_driver_lite.py
src/ohos/drivers/jsunit_driver.py
src/ohos/drivers/ltp_posix_driver.py
src/ohos/drivers/oh_jsunit_driver.py
src/ohos/drivers/oh_kernel_driver.py
src/ohos/drivers/oh_rust_driver.py
src/ohos/drivers/oh_yara_driver.py
src/ohos/drivers/opensource_driver_lite.py
src/ohos/environment/__init__.py
src/ohos/environment/device.py
src/ohos/environment/device_lite.py
src/ohos/environment/dmlib.py
src/ohos/environment/dmlib_lite.py
src/ohos/environment/emulator.py
src/ohos/environment/native_device.py
src/ohos/executor/__init__.py
src/ohos/executor/bean.py
src/ohos/executor/listener.py
src/ohos/managers/__init__.py
src/ohos/managers/manager_device.py
src/ohos/managers/manager_lite.py
src/ohos/parser/__init__.py
src/ohos/parser/build_only_parser_lite.py
src/ohos/parser/c_parser_lite.py
src/ohos/parser/constants.py
src/ohos/parser/cpp_parser.py
src/ohos/parser/cpp_parser_lite.py
src/ohos/parser/jsunit_parser.py
src/ohos/parser/jsunit_parser_lite.py
src/ohos/parser/junit_parser.py
src/ohos/parser/oh_jsunit_parser.py
src/ohos/parser/oh_kernel_parser.py
src/ohos/parser/oh_rust_parser.py
src/ohos/parser/oh_yara_parser.py
src/ohos/parser/opensource_parser_lite.py
src/ohos/proxy/__init__.py
src/ohos/proxy/proxy_base.py
src/ohos/proxy/ui_proxy.py
src/ohos/testkit/__init__.py
src/ohos/testkit/kit.py
src/ohos/testkit/kit_lite.py
src/xdevice_ohos.egg-info/PKG-INFO
src/xdevice_ohos.egg-info/SOURCES.txt
src/xdevice_ohos.egg-info/dependency_links.txt
src/xdevice_ohos.egg-info/entry_points.txt
src/xdevice_ohos.egg-info/not-zip-safe
src/xdevice_ohos.egg-info/requires.txt
src/xdevice_ohos.egg-info/top_level.txt