Metadata-Version: 2.1
Name: xdevice-ohos
Version: 6.0.7.210
Summary: plugin for ohos
Home-page: UNKNOWN
License: UNKNOWN
Platform: UNKNOWN
